torchctr/__init__.py
torchctr/dashboard/__init__.py
torchctr/dashboard/dashboard.py
torchctr/dashboard/div_builder.py
torchctr/dashboard/metric_logger.py
torchctr/datasets/__init__.py
torchctr/datasets/avazu.py
torchctr/datasets/base.py
torchctr/datasets/criteo.py
torchctr/datasets/movielens.py
torchctr/datasets/titanic.py
torchctr/layers/__init__.py
torchctr/layers/embedding.py
torchctr/layers/linear.py
torchctr/layers/perceptron.py
torchctr/models/__init__.py
torchctr/models/checker.py
torchctr/models/deep_factorization_machine.py
torchctr/models/factorization_machine.py
torchctr/models/fieldaware_factorization_machine.py
torchctr/models/fieldaware_neural_factorization_machine.py
torchctr/models/logistic_regression.py
torchctr/models/neural_factorization_machine.py
torchctr/models/wide_and_deep.py
torchctr/progressbar/__init__.py
torchctr/progressbar/progressbar.py
torchctr/trainer/__init__.py
torchctr/trainer/trainer.py
TorchCTR-0.2.dist-info/METADATA
TorchCTR-0.2.dist-info/WHEEL
TorchCTR-0.2.dist-info/entry_points.txt
TorchCTR-0.2.dist-info/top_level.txt
TorchCTR-0.2.dist-info/RECORD
